{
  "type": "FeatureCollection",
  "features": [
    {
      "type": "Feature",
      "properties": {
        "id": 1,
        "name": "Homestreet Bank Hydroplane ",
        "type": "Sponsor",
        "show_label": "",
        "icon": "",
        "show_icon": "",
        "rotate": "",
        "left_panel": "",
        "description": "",
        "details": ""
      },
      "geometry": {
        "type": "Point",
        "coordinates": [
          -122.38707042030396,
          47.668687469159366
        ]
      }
    },
    {
      "type": "Feature",
      "properties": {
        "id": 2,
        "name": "Homestreet Bank ",
        "type": "Sponsor",
        "show_label": "",
        "icon": "",
        "show_icon": "",
        "rotate": "",
        "left_panel": "",
        "description": "",
        "details": ""
      },
      "geometry": {
        "type": "Point",
        "coordinates": [
          -122.3869468818363,
          47.668687469159366
        ]
      }
    },
    {
      "type": "Feature",
      "properties": {
        "id": 3,
        "name": "Bobbie's Boat Sauce",
        "type": "Arts/Crafts",
        "show_label": "",
        "icon": "",
        "show_icon": "",
        "rotate": "",
        "left_panel": "",
        "description": "",
        "details": ""
      },
      "geometry": {
        "type": "Point",
        "coordinates": [
          -122.38689625893039,
          47.668687469159366
        ]
      }
    },
    {
      "type": "Feature",
      "properties": {
        "id": 4,
        "name": "Pacari",
        "type": "Arts/Crafts",
        "show_label": "",
        "icon": "",
        "show_icon": "",
        "rotate": "",
        "left_panel": "",
        "description": "",
        "details": ""
      },
      "geometry": {
        "type": "Point",
        "coordinates": [
          -122.38682752324165,
          47.668687469159366
        ]
      }
    },
    {
      "type": "Feature",
      "properties": {
        "id": 5,
        "name": "Pacari",
        "type": "Arts/Crafts",
        "show_label": "",
        "icon": "",
        "show_icon": "",
        "rotate": "",
        "left_panel": "",
        "description": "",
        "details": ""
      },
      "geometry": {
        "type": "Point",
        "coordinates": [
          -122.3867806931904,
          47.668687469159366
        ]
      }
    },
    {
      "type": "Feature",
      "properties": {
        "id": 6,
        "name": "Porto-Pies",
        "type": "Arts/Crafts",
        "show_label": "",
        "icon": "",
        "show_icon": "",
        "rotate": "",
        "left_panel": "",
        "description": "",
        "details": ""
      },
      "geometry": {
        "type": "Point",
        "coordinates": [
          -122.38671514104315,
          47.668687469159366
        ]
      }
    },
    {
      "type": "Feature",
      "properties": {
        "id": 7,
        "name": "Stoll & Heart",
        "type": "Arts/Crafts",
        "show_label": "",
        "icon": "",
        "show_icon": "",
        "rotate": "",
        "left_panel": "",
        "description": "",
        "details": ""
      },
      "geometry": {
        "type": "Point",
        "coordinates": [
          -122.38667099367868,
          47.668687469159366
        ]
      }
    },
    {
      "type": "Feature",
      "properties": {
        "id": 8,
        "name": "Sound Transit",
        "type": "Government",
        "show_label": "",
        "icon": "",
        "show_icon": "",
        "rotate": "",
        "left_panel": "",
        "description": "",
        "details": ""
      },
      "geometry": {
        "type": "Point",
        "coordinates": [
          -122.38660014140119,
          47.668687469159366
        ]
      }
    },
    {
      "type": "Feature",
      "properties": {
        "id": 9,
        "name": "National Nordic Museum",
        "type": "Non-Profit",
        "show_label": "",
        "icon": "",
        "show_icon": "",
        "rotate": "",
        "left_panel": "",
        "description": "",
        "details": ""
      },
      "geometry": {
        "type": "Point",
        "coordinates": [
          -122.38655132152624,
          47.668687469159366
        ]
      }
    },
    {
      "type": "Feature",
      "properties": {
        "id": 10,
        "name": "Predatory Perennials",
        "type": "Arts/Crafts",
        "show_label": "",
        "icon": "",
        "show_icon": "",
        "rotate": "",
        "left_panel": "",
        "description": "",
        "details": ""
      },
      "geometry": {
        "type": "Point",
        "coordinates": [
          -122.38648374443447,
          47.668687469159366
        ]
      }
    },
    {
      "type": "Feature",
      "properties": {
        "id": 11,
        "name": "Renee Staeck",
        "type": "Arts/Crafts",
        "show_label": "",
        "icon": "",
        "show_icon": "",
        "rotate": "",
        "left_panel": "",
        "description": "",
        "details": ""
      },
      "geometry": {
        "type": "Point",
        "coordinates": [
          -122.3864327066864,
          47.668687469159366
        ]
      }
    },
    {
      "type": "Feature",
      "properties": {
        "id": 12,
        "name": "Powerslide Design Co.",
        "type": "Arts/Crafts",
        "show_label": "",
        "icon": "",
        "show_icon": "",
        "rotate": "",
        "left_panel": "",
        "description": "",
        "details": ""
      },
      "geometry": {
        "type": "Point",
        "coordinates": [
          -122.38636890950133,
          47.668687469159366
        ]
      }
    },
    {
      "type": "Feature",
      "properties": {
        "id": 13,
        "name": "Unusal Cards",
        "type": "Arts/Crafts",
        "show_label": "",
        "icon": "",
        "show_icon": "",
        "rotate": "",
        "left_panel": "",
        "description": "",
        "details": ""
      },
      "geometry": {
        "type": "Point",
        "coordinates": [
          -122.3863223098183,
          47.668687469159366
        ]
      }
    },
    {
      "type": "Feature",
      "properties": {
        "id": 14,
        "name": "Kundalini Crystals",
        "type": "Arts/Crafts",
        "show_label": "",
        "icon": "",
        "show_icon": "",
        "rotate": "",
        "left_panel": "",
        "description": "",
        "details": ""
      },
      "geometry": {
        "type": "Point",
        "coordinates": [
          -122.38625530993497,
          47.668687469159366
        ]
      }
    },
    {
      "type": "Feature",
      "properties": {
        "id": 15,
        "name": "Mandala Moon Candle Co.",
        "type": "Arts/Crafts",
        "show_label": "",
        "icon": "",
        "show_icon": "",
        "rotate": "",
        "left_panel": "",
        "description": "",
        "details": ""
      },
      "geometry": {
        "type": "Point",
        "coordinates": [
          -122.38620300726733,
          47.668687469159366
        ]
      }
    },
    {
      "type": "Feature",
      "properties": {
        "id": 16,
        "name": "BECU",
        "type": "Sponsor",
        "show_label": "",
        "icon": "",
        "show_icon": "",
        "rotate": "",
        "left_panel": "",
        "description": "",
        "details": ""
      },
      "geometry": {
        "type": "Point",
        "coordinates": [
          -122.38613827624297,
          47.66873434964762
        ]
      }
    },
    {
      "type": "Feature",
      "properties": {
        "id": 17,
        "name": "Healing Stone Foundary",
        "type": "Arts/Crafts",
        "show_label": "",
        "icon": "",
        "show_icon": "",
        "rotate": "",
        "left_panel": "",
        "description": "",
        "details": ""
      },
      "geometry": {
        "type": "Point",
        "coordinates": [
          -122.38613827624297,
          47.668687469159366
        ]
      }
    },
    {
      "type": "Feature",
      "properties": {
        "id": 18,
        "name": "Ballard Food Bank",
        "type": "Non-Profit",
        "show_label": "",
        "icon": "",
        "show_icon": "",
        "rotate": "",
        "left_panel": "",
        "description": "",
        "details": ""
      },
      "geometry": {
        "type": "Point",
        "coordinates": [
          -122.3860880449681,
          47.66873434964762
        ]
      }
    },
    {
      "type": "Feature",
      "properties": {
        "id": 19,
        "name": "Hot Mama Salsa",
        "type": "Arts/Crafts",
        "show_label": "",
        "icon": "",
        "show_icon": "",
        "rotate": "",
        "left_panel": "",
        "description": "",
        "details": ""
      },
      "geometry": {
        "type": "Point",
        "coordinates": [
          -122.3860880449681,
          47.668687469159366
        ]
      }
    },
    {
      "type": "Feature",
      "properties": {
        "id": 20,
        "name": "Leif Erikson Lodge",
        "type": "Non-Profit",
        "show_label": "",
        "icon": "",
        "show_icon": "",
        "rotate": "",
        "left_panel": "",
        "description": "",
        "details": ""
      },
      "geometry": {
        "type": "Point",
        "coordinates": [
          -122.38602538533657,
          47.66873434964762
        ]
      }
    },
    {
      "type": "Feature",
      "properties": {
        "id": 21,
        "name": "Art by IamKobold",
        "type": "Arts/Crafts",
        "show_label": "",
        "icon": "",
        "show_icon": "",
        "rotate": "",
        "left_panel": "",
        "description": "",
        "details": ""
      },
      "geometry": {
        "type": "Point",
        "coordinates": [
          -122.38602538533657,
          47.668687469159366
        ]
      }
    },
    {
      "type": "Feature",
      "properties": {
        "id": 22,
        "name": "Wag & Wood",
        "type": "Arts/Crafts",
        "show_label": "",
        "icon": "",
        "show_icon": "",
        "rotate": "",
        "left_panel": "",
        "description": "",
        "details": ""
      },
      "geometry": {
        "type": "Point",
        "coordinates": [
          -122.3859730826689,
          47.66873434964762
        ]
      }
    },
    {
      "type": "Feature",
      "properties": {
        "id": 23,
        "name": "Olive Branch / A Taste of Eden",
        "type": "Arts/Crafts",
        "show_label": "",
        "icon": "",
        "show_icon": "",
        "rotate": "",
        "left_panel": "",
        "description": "",
        "details": ""
      },
      "geometry": {
        "type": "Point",
        "coordinates": [
          -122.3859730826689,
          47.668687469159366
        ]
      }
    },
    {
      "type": "Feature",
      "properties": {
        "id": 24,
        "name": "Puget Sound Maritime",
        "type": "Non-Profit",
        "show_label": "",
        "icon": "",
        "show_icon": "",
        "rotate": "",
        "left_panel": "",
        "description": "",
        "details": ""
      },
      "geometry": {
        "type": "Point",
        "coordinates": [
          -122.38590994135373,
          47.66873434964762
        ]
      }
    },
    {
      "type": "Feature",
      "properties": {
        "id": 25,
        "name": "Columbia State Bank",
        "type": "Sponsor",
        "show_label": "",
        "icon": "",
        "show_icon": "",
        "rotate": "",
        "left_panel": "",
        "description": "",
        "details": ""
      },
      "geometry": {
        "type": "Point",
        "coordinates": [
          -122.38590994135373,
          47.668687469159366
        ]
      }
    },
    {
      "type": "Feature",
      "properties": {
        "id": 26,
        "name": "Seattle Subway Foundation",
        "type": "Non-Profit",
        "show_label": "",
        "icon": "",
        "show_icon": "",
        "rotate": "",
        "left_panel": "",
        "description": "",
        "details": ""
      },
      "geometry": {
        "type": "Point",
        "coordinates": [
          -122.3858587923162,
          47.66873434964762
        ]
      }
    },
    {
      "type": "Feature",
      "properties": {
        "id": 27,
        "name": "Summit & Terrace Artisanal Fragrances",
        "type": "Arts/Crafts",
        "show_label": "",
        "icon": "",
        "show_icon": "",
        "rotate": "",
        "left_panel": "",
        "description": "",
        "details": ""
      },
      "geometry": {
        "type": "Point",
        "coordinates": [
          -122.3858587923162,
          47.668687469159366
        ]
      }
    },
    {
      "type": "Feature",
      "properties": {
        "id": 28,
        "name": "Ballard High School ABC",
        "type": "Non-Profit",
        "show_label": "",
        "icon": "",
        "show_icon": "",
        "rotate": "",
        "left_panel": "",
        "description": "",
        "details": ""
      },
      "geometry": {
        "type": "Point",
        "coordinates": [
          -122.38579515339737,
          47.66873434964762
        ]
      }
    },
    {
      "type": "Feature",
      "properties": {
        "id": 29,
        "name": "The Polyclinic",
        "type": "Sponsor",
        "show_label": "",
        "icon": "",
        "show_icon": "",
        "rotate": "",
        "left_panel": "",
        "description": "",
        "details": ""
      },
      "geometry": {
        "type": "Point",
        "coordinates": [
          -122.38579515339737,
          47.668687469159366
        ]
      }
    },
    {
      "type": "Feature",
      "properties": {
        "id": 30,
        "name": "All the Jawns",
        "type": "Arts/Crafts",
        "show_label": "",
        "icon": "",
        "show_icon": "",
        "rotate": "",
        "left_panel": "",
        "description": "",
        "details": ""
      },
      "geometry": {
        "type": "Point",
        "coordinates": [
          -122.38574519387232,
          47.66873434964762
        ]
      }
    },
    {
      "type": "Feature",
      "properties": {
        "id": 31,
        "name": "Alaska USA Federal Credit Union",
        "type": "Sponsor",
        "show_label": "",
        "icon": "",
        "show_icon": "",
        "rotate": "",
        "left_panel": "",
        "description": "",
        "details": ""
      },
      "geometry": {
        "type": "Point",
        "coordinates": [
          -122.38574519387232,
          47.668687469159366
        ]
      }
    },
    {
      "type": "Feature",
      "properties": {
        "id": 32,
        "name": "Sea to Sno Candle Co.",
        "type": "Arts/Crafts",
        "show_label": "",
        "icon": "",
        "show_icon": "",
        "rotate": "",
        "left_panel": "",
        "description": "",
        "details": ""
      },
      "geometry": {
        "type": "Point",
        "coordinates": [
          -122.38567977068477,
          47.66873434964762
        ]
      }
    },
    {
      "type": "Feature",
      "properties": {
        "id": 33,
        "name": "Salmon Bay Eagles",
        "type": "Non-Profit",
        "show_label": "",
        "icon": "",
        "show_icon": "",
        "rotate": "",
        "left_panel": "",
        "description": "",
        "details": ""
      },
      "geometry": {
        "type": "Point",
        "coordinates": [
          -122.38567977068477,
          47.668687469159366
        ]
      }
    },
    {
      "type": "Feature",
      "properties": {
        "id": 34,
        "name": "Splat hot Sauce",
        "type": "Arts/Crafts",
        "show_label": "",
        "icon": "",
        "show_icon": "",
        "rotate": "",
        "left_panel": "",
        "description": "",
        "details": ""
      },
      "geometry": {
        "type": "Point",
        "coordinates": [
          -122.38562683737848,
          47.66873434964762
        ]
      }
    },
    {
      "type": "Feature",
      "properties": {
        "id": 35,
        "name": "Neptune Snacks",
        "type": "Arts/Crafts",
        "show_label": "",
        "icon": "",
        "show_icon": "",
        "rotate": "",
        "left_panel": "",
        "description": "",
        "details": ""
      },
      "geometry": {
        "type": "Point",
        "coordinates": [
          -122.38562683737848,
          47.668687469159366
        ]
      }
    },
    {
      "type": "Feature",
      "properties": {
        "id": 36,
        "name": "Cascade Adventures",
        "type": "Sponsor",
        "show_label": "",
        "icon": "",
        "show_icon": "",
        "rotate": "",
        "left_panel": "",
        "description": "",
        "details": ""
      },
      "geometry": {
        "type": "Point",
        "coordinates": [
          -122.38556342376856,
          47.66873434964762
        ]
      }
    },
    {
      "type": "Feature",
      "properties": {
        "id": 37,
        "name": "Neptune Snacks",
        "type": "Arts/Crafts",
        "show_label": "",
        "icon": "",
        "show_icon": "",
        "rotate": "",
        "left_panel": "",
        "description": "",
        "details": ""
      },
      "geometry": {
        "type": "Point",
        "coordinates": [
          -122.38556342376856,
          47.668687469159366
        ]
      }
    },
    {
      "type": "Feature",
      "properties": {
        "id": 38,
        "name": "Snapdragon Thistle",
        "type": "Arts/Crafts",
        "show_label": "",
        "icon": "",
        "show_icon": "",
        "rotate": "",
        "left_panel": "",
        "description": "",
        "details": ""
      },
      "geometry": {
        "type": "Point",
        "coordinates": [
          -122.38551285128585,
          47.66873434964762
        ]
      }
    },
    {
      "type": "Feature",
      "properties": {
        "id": 39,
        "name": "Neptune Snacks",
        "type": "Arts/Crafts",
        "show_label": "",
        "icon": "",
        "show_icon": "",
        "rotate": "",
        "left_panel": "",
        "description": "",
        "details": ""
      },
      "geometry": {
        "type": "Point",
        "coordinates": [
          -122.38551285128585,
          47.668687469159366
        ]
      }
    },
    {
      "type": "Feature",
      "properties": {
        "id": 40,
        "name": "Atelier Adesso",
        "type": "Arts/Crafts",
        "show_label": "",
        "icon": "",
        "show_icon": "",
        "rotate": "",
        "left_panel": "",
        "description": "",
        "details": ""
      },
      "geometry": {
        "type": "Point",
        "coordinates": [
          -122.38544863226024,
          47.66873434964762
        ]
      }
    },
    {
      "type": "Feature",
      "properties": {
        "id": 41,
        "name": "Steele Barber",
        "type": "Sponsor",
        "show_label": "",
        "icon": "",
        "show_icon": "",
        "rotate": "",
        "left_panel": "",
        "description": "",
        "details": ""
      },
      "geometry": {
        "type": "Point",
        "coordinates": [
          -122.38544863226024,
          47.668687469159366
        ]
      }
    },
    {
      "type": "Feature",
      "properties": {
        "id": 42,
        "name": "Ruby Laine Apparel",
        "type": "Arts/Crafts",
        "show_label": "",
        "icon": "",
        "show_icon": "",
        "rotate": "",
        "left_panel": "",
        "description": "",
        "details": ""
      },
      "geometry": {
        "type": "Point",
        "coordinates": [
          -122.38539805977754,
          47.66873434964762
        ]
      }
    },
    {
      "type": "Feature",
      "properties": {
        "id": 43,
        "name": "Nomad Boxing Club",
        "type": "Non-Profit",
        "show_label": "",
        "icon": "",
        "show_icon": "",
        "rotate": "",
        "left_panel": "",
        "description": "",
        "details": ""
      },
      "geometry": {
        "type": "Point",
        "coordinates": [
          -122.38539805977754,
          47.668687469159366
        ]
      }
    },
    {
      "type": "Feature",
      "properties": {
        "id": 44,
        "name": "Aviv Jewelry",
        "type": "Arts/Crafts",
        "show_label": "",
        "icon": "",
        "show_icon": "",
        "rotate": "",
        "left_panel": "",
        "description": "",
        "details": ""
      },
      "geometry": {
        "type": "Point",
        "coordinates": [
          -122.38533228438806,
          47.66873434964762
        ]
      }
    },
    {
      "type": "Feature",
      "properties": {
        "id": 45,
        "name": "Marmalade Originals",
        "type": "Arts/Crafts",
        "show_label": "",
        "icon": "",
        "show_icon": "",
        "rotate": "",
        "left_panel": "",
        "description": "",
        "details": ""
      },
      "geometry": {
        "type": "Point",
        "coordinates": [
          -122.38533228438806,
          47.668687469159366
        ]
      }
    },
    {
      "type": "Feature",
      "properties": {
        "id": 46,
        "name": "Puddles Barkery",
        "type": "Arts/Crafts",
        "show_label": "",
        "icon": "",
        "show_icon": "",
        "rotate": "",
        "left_panel": "",
        "description": "",
        "details": ""
      },
      "geometry": {
        "type": "Point",
        "coordinates": [
          -122.38528232204497,
          47.66873434964762
        ]
      }
    },
    {
      "type": "Feature",
      "properties": {
        "id": 47,
        "name": "Swedish Ballard Hospital",
        "type": "Sponsor",
        "show_label": "",
        "icon": "",
        "show_icon": "",
        "rotate": "",
        "left_panel": "",
        "description": "",
        "details": ""
      },
      "geometry": {
        "type": "Point",
        "coordinates": [
          -122.38528232204497,
          47.668687469159366
        ]
      }
    },
    {
      "type": "Feature",
      "properties": {
        "id": 48,
        "name": "Murder Hornet Hot Sauce",
        "type": "Arts/Crafts",
        "show_label": "",
        "icon": "",
        "show_icon": "",
        "rotate": "",
        "left_panel": "",
        "description": "",
        "details": ""
      },
      "geometry": {
        "type": "Point",
        "coordinates": [
          -122.38521586270183,
          47.66873434964762
        ]
      }
    },
    {
      "type": "Feature",
      "properties": {
        "id": 49,
        "name": "Caricatures by Over the Line Art",
        "type": "Arts/Crafts",
        "show_label": "",
        "icon": "",
        "show_icon": "",
        "rotate": "",
        "left_panel": "",
        "description": "",
        "details": ""
      },
      "geometry": {
        "type": "Point",
        "coordinates": [
          -122.38521586270183,
          47.668687469159366
        ]
      }
    },
    {
      "type": "Feature",
      "properties": {
        "id": 50,
        "name": "Cat's Creations",
        "type": "Arts/Crafts",
        "show_label": "",
        "icon": "",
        "show_icon": "",
        "rotate": "",
        "left_panel": "",
        "description": "",
        "details": ""
      },
      "geometry": {
        "type": "Point",
        "coordinates": [
          -122.38516872841589,
          47.66873434964762
        ]
      }
    },
    {
      "type": "Feature",
      "properties": {
        "id": 51,
        "name": "Bling! Bling!",
        "type": "Arts/Crafts",
        "show_label": "",
        "icon": "",
        "show_icon": "",
        "rotate": "",
        "left_panel": "",
        "description": "",
        "details": ""
      },
      "geometry": {
        "type": "Point",
        "coordinates": [
          -122.38516872841589,
          47.668687469159366
        ]
      }
    },
    {
      "type": "Feature",
      "properties": {
        "id": 52,
        "name": "Veteran's of Foreign Wars",
        "type": "Non-Profit",
        "show_label": "",
        "icon": "",
        "show_icon": "",
        "rotate": "",
        "left_panel": "",
        "description": "",
        "details": ""
      },
      "geometry": {
        "type": "Point",
        "coordinates": [
          -122.38510326197425,
          47.66873434964762
        ]
      }
    },
    {
      "type": "Feature",
      "properties": {
        "id": 53,
        "name": "UW Medicine",
        "type": "Sponsor",
        "show_label": "",
        "icon": "",
        "show_icon": "",
        "rotate": "",
        "left_panel": "",
        "description": "",
        "details": ""
      },
      "geometry": {
        "type": "Point",
        "coordinates": [
          -122.38510326197425,
          47.668687469159366
        ]
      }
    },
    {
      "type": "Feature",
      "properties": {
        "id": 54,
        "name": "Rock Lobster Designs",
        "type": "Arts/Crafts",
        "show_label": "",
        "icon": "",
        "show_icon": "",
        "rotate": "",
        "left_panel": "",
        "description": "",
        "details": ""
      },
      "geometry": {
        "type": "Point",
        "coordinates": [
          -122.38505483473426,
          47.66873434964762
        ]
      }
    },
    {
      "type": "Feature",
      "properties": {
        "id": 55,
        "name": "Novo Painting and Property Services",
        "type": "Sponsor",
        "show_label": "",
        "icon": "",
        "show_icon": "",
        "rotate": "",
        "left_panel": "",
        "description": "",
        "details": ""
      },
      "geometry": {
        "type": "Point",
        "coordinates": [
          -122.38505483473426,
          47.668687469159366
        ]
      }
    },
    {
      "type": "Feature",
      "properties": {
        "id": 56,
        "name": "Macadons LLC",
        "type": "Arts/Crafts",
        "show_label": "",
        "icon": "",
        "show_icon": "",
        "rotate": "",
        "left_panel": "",
        "description": "",
        "details": ""
      },
      "geometry": {
        "type": "Point",
        "coordinates": [
          -122.38498514675483,
          47.66873434964762
        ]
      }
    },
    {
      "type": "Feature",
      "properties": {
        "id": 57,
        "name": "Lumen",
        "type": "Sponsor",
        "show_label": "",
        "icon": "",
        "show_icon": "",
        "rotate": "",
        "left_panel": "",
        "description": "",
        "details": ""
      },
      "geometry": {
        "type": "Point",
        "coordinates": [
          -122.38498514675483,
          47.668687469159366
        ]
      }
    },
    {
      "type": "Feature",
      "properties": {
        "id": 58,
        "name": "Z-Ultimate Self Defense Studios",
        "type": "Sponsor",
        "show_label": "",
        "icon": "",
        "show_icon": "",
        "rotate": "",
        "left_panel": "",
        "description": "",
        "details": ""
      },
      "geometry": {
        "type": "Point",
        "coordinates": [
          -122.38493790066703,
          47.66873434964762
        ]
      }
    },
    {
      "type": "Feature",
      "properties": {
        "id": 59,
        "name": "Xtreme Pet Products",
        "type": "Arts/Crafts",
        "show_label": "",
        "icon": "",
        "show_icon": "",
        "rotate": "",
        "left_panel": "",
        "description": "",
        "details": ""
      },
      "geometry": {
        "type": "Point",
        "coordinates": [
          -122.38493908181924,
          47.668687469159366
        ]
      }
    },
    {
      "type": "Feature",
      "properties": {
        "id": 60,
        "name": "SeafoodFest Info Booth & Token Sales",
        "type": "Event Support",
        "show_label": "",
        "icon": "svg_info",
        "show_icon": "true",
        "rotate": "",
        "left_panel": "",
        "description": "",
        "details": ""
      },
      "geometry": {
        "type": "Point",
        "coordinates": [
          -122.38488711112268,
          47.668725110209266
        ]
      }
    },
    {
      "type": "Feature",
      "properties": {
        "id": 61,
        "name": "Gravity Payments",
        "type": "Sponsor",
        "show_label": "",
        "icon": "",
        "show_icon": "",
        "rotate": "",
        "left_panel": "",
        "description": "",
        "details": ""
      },
      "geometry": {
        "type": "Point",
        "coordinates": [
          -122.38483588804061,
          47.6686043576445
        ]
      }
    },
    {
      "type": "Feature",
      "properties": {
        "id": 62,
        "name": "Island Creamery Concessions",
        "type": "Food Vendor",
        "show_label": "",
        "icon": "",
        "show_icon": "",
        "rotate": "",
        "left_panel": "",
        "description": "",
        "details": ""
      },
      "geometry": {
        "type": "Point",
        "coordinates": [
          -122.38482327039924,
          47.668486181901976
        ]
      }
    },
    {
      "type": "Feature",
      "properties": {
        "id": 63,
        "name": "Puffle Up",
        "type": "Food Vendor",
        "show_label": "",
        "icon": "",
        "show_icon": "",
        "rotate": "",
        "left_panel": "",
        "description": "",
        "details": ""
      },
      "geometry": {
        "type": "Point",
        "coordinates": [
          -122.38482583389883,
          47.66837051900958
        ]
      }
    },
    {
      "type": "Feature",
      "properties": {
        "id": 64,
        "name": "Seattle Pops",
        "type": "Food Vendor",
        "show_label": "",
        "icon": "",
        "show_icon": "",
        "rotate": "",
        "left_panel": "",
        "description": "",
        "details": ""
      },
      "geometry": {
        "type": "Point",
        "coordinates": [
          -122.38482583389883,
          47.668343551368224
        ]
      }
    },
    {
      "type": "Feature",
      "properties": {
        "id": 65,
        "name": "Raspados del Sur",
        "type": "Food Vendor",
        "show_label": "",
        "icon": "",
        "show_icon": "",
        "rotate": "",
        "left_panel": "",
        "description": "",
        "details": ""
      },
      "geometry": {
        "type": "Point",
        "coordinates": [
          -122.38482583389883,
          47.66830696175206
        ]
      }
    },
    {
      "type": "Feature",
      "properties": {
        "id": 66,
        "name": "Kottu",
        "type": "Food Vendor",
        "show_label": "",
        "icon": "",
        "show_icon": "",
        "rotate": "",
        "left_panel": "",
        "description": "",
        "details": ""
      },
      "geometry": {
        "type": "Point",
        "coordinates": [
          -122.38482583389883,
          47.66826841195013
        ]
      }
    },
    {
      "type": "Feature",
      "properties": {
        "id": 67,
        "name": "Skal Beer Hall",
        "type": "Food Vendor",
        "show_label": "",
        "icon": "",
        "show_icon": "",
        "rotate": "",
        "left_panel": "",
        "description": "",
        "details": ""
      },
      "geometry": {
        "type": "Point",
        "coordinates": [
          -122.38482583389883,
          47.6682390095397
        ]
      }
    },
    {
      "type": "Feature",
      "properties": {
        "id": 68,
        "name": "Ballard Seattle Chiropractic Center ",
        "type": "Sponsor",
        "show_label": "",
        "icon": "",
        "show_icon": "",
        "rotate": "",
        "left_panel": "",
        "description": "",
        "details": ""
      },
      "geometry": {
        "type": "Point",
        "coordinates": [
          -122.3846889,
          47.66835254
        ]
      }
    },
    {
      "type": "Feature",
      "properties": {
        "id": 69,
        "name": "Ballard FC",
        "type": "Sponsor",
        "show_label": "",
        "icon": "",
        "show_icon": "",
        "rotate": "",
        "left_panel": "",
        "description": "",
        "details": ""
      },
      "geometry": {
        "type": "Point",
        "coordinates": [
          -122.38468840585838,
          47.668377527417405
        ]
      }
    },
    {
      "type": "Feature",
      "properties": {
        "id": 70,
        "name": "Carter VW/Subaru",
        "type": "Sponsor",
        "show_label": "",
        "icon": "",
        "show_icon": "",
        "rotate": "",
        "left_panel": "",
        "description": "",
        "details": ""
      },
      "geometry": {
        "type": "Point",
        "coordinates": [
          -122.38468840585838,
          47.66840627636483
        ]
      }
    },
    {
      "type": "Feature",
      "properties": {
        "id": 71,
        "name": "The Jyst",
        "type": "Sponsor",
        "show_label": "",
        "icon": "",
        "show_icon": "",
        "rotate": "",
        "left_panel": "",
        "description": "",
        "details": ""
      },
      "geometry": {
        "type": "Point",
        "coordinates": [
          -122.38468840585838,
          47.668438292219456
        ]
      }
    },
    {
      "type": "Feature",
      "properties": {
        "id": 72,
        "name": "Omodo Teahouse",
        "type": "Food Vendor",
        "show_label": "",
        "icon": "",
        "show_icon": "",
        "rotate": "",
        "left_panel": "",
        "description": "",
        "details": ""
      },
      "geometry": {
        "type": "Point",
        "coordinates": [
          -122.38465444716105,
          47.668519311845465
        ]
      }
    },
    {
      "type": "Feature",
      "properties": {
        "id": 73,
        "name": "Biringer Farm",
        "type": "Food Vendor",
        "show_label": "",
        "icon": "",
        "show_icon": "",
        "rotate": "",
        "left_panel": "",
        "description": "",
        "details": ""
      },
      "geometry": {
        "type": "Point",
        "coordinates": [
          -122.38461466697272,
          47.6685787697168
        ]
      }
    },
    {
      "type": "Feature",
      "properties": {
        "id": 74,
        "name": "Big Island Poke",
        "type": "Food Vendor",
        "show_label": "",
        "icon": "",
        "show_icon": "",
        "rotate": "",
        "left_panel": "",
        "description": "",
        "details": ""
      },
      "geometry": {
        "type": "Point",
        "coordinates": [
          -122.38454383883257,
          47.668568315590484
        ]
      }
    },
    {
      "type": "Feature",
      "properties": {
        "id": 75,
        "name": "Alaska Weathervane Scallops",
        "type": "Food Vendor",
        "show_label": "",
        "icon": "",
        "show_icon": "",
        "rotate": "",
        "left_panel": "",
        "description": "",
        "details": ""
      },
      "geometry": {
        "type": "Point",
        "coordinates": [
          -122.3843934503158,
          47.66850232386979
        ]
      }
    },
    {
      "type": "Feature",
      "properties": {
        "id": 76,
        "name": "Paella House",
        "type": "Food Vendor",
        "show_label": "",
        "icon": "",
        "show_icon": "",
        "rotate": "",
        "left_panel": "",
        "description": "",
        "details": ""
      },
      "geometry": {
        "type": "Point",
        "coordinates": [
          -122.38431291969067,
          47.66843241175783
        ]
      }
    },
    {
      "type": "Feature",
      "properties": {
        "id": 77,
        "name": "Kaleenka Piroshky",
        "type": "Food Vendor",
        "show_label": "",
        "icon": "",
        "show_icon": "",
        "rotate": "",
        "left_panel": "",
        "description": "",
        "details": ""
      },
      "geometry": {
        "type": "Point",
        "coordinates": [
          -122.38425470478091,
          47.66838079434404
        ]
      }
    },
    {
      "type": "Feature",
      "properties": {
        "id": 78,
        "name": "King Co. Metro",
        "type": "Government",
        "show_label": "",
        "icon": "",
        "show_icon": "",
        "rotate": "",
        "left_panel": "",
        "description": "",
        "details": ""
      },
      "geometry": {
        "type": "Point",
        "coordinates": [
          -122.3841632800104,
          47.66827083525231
        ]
      }
    },
    {
      "type": "Feature",
      "properties": {
        "id": 79,
        "name": "King Co. Metro Bus",
        "type": "Government",
        "show_label": "",
        "icon": "",
        "show_icon": "",
        "rotate": "",
        "left_panel": "",
        "description": "",
        "details": ""
      },
      "geometry": {
        "type": "Point",
        "coordinates": [
          -122.38411273422301,
          47.6682254503721
        ]
      }
    },
    {
      "type": "Feature",
      "properties": {
        "id": 80,
        "name": "Glow Tea",
        "type": "Food Vendor",
        "show_label": "",
        "icon": "",
        "show_icon": "",
        "rotate": "",
        "left_panel": "",
        "description": "",
        "details": ""
      },
      "geometry": {
        "type": "Point",
        "coordinates": [
          -122.38416321080568,
          47.66857295580398
        ]
      }
    },
    {
      "type": "Feature",
      "properties": {
        "id": 81,
        "name": "Sugar + Spoon",
        "type": "Food Vendor",
        "show_label": "",
        "icon": "",
        "show_icon": "",
        "rotate": "",
        "left_panel": "",
        "description": "",
        "details": ""
      },
      "geometry": {
        "type": "Point",
        "coordinates": [
          -122.38411706090375,
          47.66863702462691
        ]
      }
    },
    {
      "type": "Feature",
      "properties": {
        "id": 82,
        "name": "Flaco's Tacos",
        "type": "Food Vendor",
        "show_label": "",
        "icon": "",
        "show_icon": "",
        "rotate": "",
        "left_panel": "",
        "description": "",
        "details": ""
      },
      "geometry": {
        "type": "Point",
        "coordinates": [
          -122.38402405110142,
          47.6686360683764
        ]
      }
    },
    {
      "type": "Feature",
      "properties": {
        "id": 83,
        "name": "Zieglers Bratwurst Haus",
        "type": "Food Vendor",
        "show_label": "",
        "icon": "",
        "show_icon": "",
        "rotate": "",
        "left_panel": "",
        "description": "",
        "details": ""
      },
      "geometry": {
        "type": "Point",
        "coordinates": [
          -122.38395522995839,
          47.66861488173659
        ]
      }
    },
    {
      "type": "Feature",
      "properties": {
        "id": 84,
        "name": "Boba Bar & Mangosteen",
        "type": "Food Vendor",
        "show_label": "",
        "icon": "",
        "show_icon": "",
        "rotate": "",
        "left_panel": "",
        "description": "",
        "details": ""
      },
      "geometry": {
        "type": "Point",
        "coordinates": [
          -122.38382467483946,
          47.668614019794326
        ]
      }
    },
    {
      "type": "Feature",
      "properties": {
        "id": 85,
        "name": "Caveman Eats",
        "type": "Food Vendor",
        "show_label": "",
        "icon": "",
        "show_icon": "",
        "rotate": "",
        "left_panel": "",
        "description": "",
        "details": ""
      },
      "geometry": {
        "type": "Point",
        "coordinates": [
          -122.38374335720086,
          47.668613844139685
        ]
      }
    },
    {
      "type": "Feature",
      "properties": {
        "id": 86,
        "name": "JJ & Sons Concession",
        "type": "Food Vendor",
        "show_label": "",
        "icon": "",
        "show_icon": "",
        "rotate": "",
        "left_panel": "",
        "description": "",
        "details": ""
      },
      "geometry": {
        "type": "Point",
        "coordinates": [
          -122.38358712078048,
          47.66861296000227
        ]
      }
    },
    {
      "type": "Feature",
      "properties": {
        "id": 87,
        "name": "Character Cotton Candy",
        "type": "Food Vendor",
        "show_label": "",
        "icon": "",
        "show_icon": "",
        "rotate": "",
        "left_panel": "",
        "description": "",
        "details": ""
      },
      "geometry": {
        "type": "Point",
        "coordinates": [
          -122.3835030944704,
          47.66861030758994
        ]
      }
    },
    {
      "type": "Feature",
      "properties": {
        "id": 88,
        "name": "Seoul Bowl",
        "type": "Food Vendor",
        "show_label": "",
        "icon": "",
        "show_icon": "",
        "rotate": "",
        "left_panel": "",
        "description": "",
        "details": ""
      },
      "geometry": {
        "type": "Point",
        "coordinates": [
          -122.38342563271573,
          47.66860853931496
        ]
      }
    },
    {
      "type": "Feature",
      "properties": {
        "id": 89,
        "name": "JJ Froyo Go",
        "type": "Food Vendor",
        "show_label": "",
        "icon": "",
        "show_icon": "",
        "rotate": "",
        "left_panel": "",
        "description": "",
        "details": ""
      },
      "geometry": {
        "type": "Point",
        "coordinates": [
          -122.38331272236154,
          47.66861649655185
        ]
      }
    },
    {
      "type": "Feature",
      "properties": {
        "id": 90,
        "name": "The Cheese Pit",
        "type": "Food Vendor",
        "show_label": "",
        "icon": "",
        "show_icon": "",
        "rotate": "",
        "left_panel": "",
        "description": "",
        "details": ""
      },
      "geometry": {
        "type": "Point",
        "coordinates": [
          -122.38318799580748,
          47.668635947570195
        ]
      }
    },
    {
      "type": "Feature",
      "properties": {
        "id": 91,
        "name": "C. Davis Texas BBQ",
        "type": "Food Vendor",
        "show_label": "",
        "icon": "",
        "show_icon": "",
        "rotate": "",
        "left_panel": "",
        "description": "",
        "details": ""
      },
      "geometry": {
        "type": "Point",
        "coordinates": [
          -122.38314728384903,
          47.66872316757554
        ]
      }
    },
    {
      "type": "Feature",
      "properties": {
        "id": 92,
        "name": "Super Tortas Ganzin",
        "type": "Food Vendor",
        "show_label": "",
        "icon": "",
        "show_icon": "",
        "rotate": "",
        "left_panel": "",
        "description": "",
        "details": ""
      },
      "geometry": {
        "type": "Point",
        "coordinates": [
          -122.38347337365114,
          47.66874428239284
        ]
      }
    },
    {
      "type": "Feature",
      "properties": {
        "id": 93,
        "name": "Mexicuban",
        "type": "Food Vendor",
        "show_label": "",
        "icon": "",
        "show_icon": "",
        "rotate": "",
        "left_panel": "",
        "description": "",
        "details": ""
      },
      "geometry": {
        "type": "Point",
        "coordinates": [
          -122.38359252184809,
          47.668743226652175
        ]
      }
    },
    {
      "type": "Feature",
      "properties": {
        "id": 94,
        "name": "Off the Rez",
        "type": "Food Vendor",
        "show_label": "",
        "icon": "",
        "show_icon": "",
        "rotate": "",
        "left_panel": "",
        "description": "",
        "details": ""
      },
      "geometry": {
        "type": "Point",
        "coordinates": [
          -122.38370226360843,
          47.668746393874095
        ]
      }
    },
    {
      "type": "Feature",
      "properties": {
        "id": 95,
        "name": "Island Blends Acai and Poke",
        "type": "Food Vendor",
        "show_label": "",
        "icon": "",
        "show_icon": "",
        "rotate": "",
        "left_panel": "",
        "description": "",
        "details": ""
      },
      "geometry": {
        "type": "Point",
        "coordinates": [
          -122.38381043762934,
          47.668746393874095
        ]
      }
    },
    {
      "type": "Feature",
      "properties": {
        "id": 96,
        "name": "Tuk Tuk Mobile Feast",
        "type": "Food Vendor",
        "show_label": "",
        "icon": "",
        "show_icon": "",
        "rotate": "",
        "left_panel": "",
        "description": "",
        "details": ""
      },
      "geometry": {
        "type": "Point",
        "coordinates": [
          -122.38409257230987,
          47.66873954999132
        ]
      }
    },
    {
      "type": "Feature",
      "properties": {
        "id": 97,
        "name": "Where Ya At Matt",
        "type": "Food Vendor",
        "show_label": "",
        "icon": "",
        "show_icon": "",
        "rotate": "",
        "left_panel": "",
        "description": "",
        "details": ""
      },
      "geometry": {
        "type": "Point",
        "coordinates": [
          -122.38419205761375,
          47.66874131301737
        ]
      }
    },
    {
      "type": "Feature",
      "properties": {
        "id": 98,
        "name": "Kornman of Washington",
        "type": "Food Vendor",
        "show_label": "",
        "icon": "",
        "show_icon": "",
        "rotate": "",
        "left_panel": "",
        "description": "",
        "details": ""
      },
      "geometry": {
        "type": "Point",
        "coordinates": [
          -122.38426928962598,
          47.66872191972759
        ]
      }
    },
    {
      "type": "Feature",
      "properties": {
        "id": 99,
        "name": "Truly Med",
        "type": "Food Vendor",
        "show_label": "",
        "icon": "",
        "show_icon": "",
        "rotate": "",
        "left_panel": "",
        "description": "",
        "details": ""
      },
      "geometry": {
        "type": "Point",
        "coordinates": [
          -122.38438971920438,
          47.66872280124092
        ]
      }
    },
    {
      "type": "Feature",
      "properties": {
        "id": 100,
        "name": "Town & Country Markets",
        "type": "Sponsor",
        "show_label": "",
        "icon": "",
        "show_icon": "",
        "rotate": "",
        "left_panel": "",
        "description": "",
        "details": ""
      },
      "geometry": {
        "type": "Point",
        "coordinates": [
          -122.3845114577999,
          47.66872280124092
        ]
      }
    },
    {
      "type": "Feature",
      "properties": {
        "id": 102,
        "name": "ILS Photo Booths",
        "type": "Kids Activities",
        "show_label": "",
        "icon": "",
        "show_icon": "",
        "rotate": "",
        "left_panel": "",
        "description": "",
        "details": ""
      },
      "geometry": {
        "type": "Point",
        "coordinates": [
          -122.38458956708135,
          47.66940303612039
        ]
      }
    },
    {
      "type": "Feature",
      "properties": {
        "id": 103,
        "name": "Fur Fighters",
        "type": "Mobile Dog Groomer",
        "show_label": "",
        "icon": "",
        "show_icon": "",
        "rotate": "",
        "left_panel": "",
        "description": "",
        "details": ""
      },
      "geometry": {
        "type": "Point",
        "coordinates": [
          -122.38439280419293,
          47.66947601822519
        ]
      }
    },
    {
      "type": "Feature",
      "properties": {
        "id": 104,
        "name": "Kids Activites",
        "type": "Kids Activities",
        "show_label": "",
        "icon": "",
        "show_icon": "",
        "rotate": "",
        "left_panel": "",
        "description": "",
        "details": ""
      },
      "geometry": {
        "type": "Point",
        "coordinates": [
          -122.38446856316598,
          47.66948948093239
        ]
      }
    },
    {
      "type": "Feature",
      "properties": {
        "id": 105,
        "name": "Hoopla Face Paint",
        "type": "Kids Activities",
        "show_label": "",
        "icon": "",
        "show_icon": "",
        "rotate": "",
        "left_panel": "",
        "description": "",
        "details": ""
      },
      "geometry": {
        "type": "Point",
        "coordinates": [
          -122.38450012940478,
          47.66954049747557
        ]
      }
    },
    {
      "type": "Feature",
      "properties": {
        "id": 106,
        "name": "All the Best Pet Care",
        "type": "Kids Activities",
        "show_label": "",
        "icon": "",
        "show_icon": "",
        "rotate": "",
        "left_panel": "",
        "description": "",
        "details": ""
      },
      "geometry": {
        "type": "Point",
        "coordinates": [
          -122.38454011330724,
          47.6694923151861
        ]
      }
    },
    {
      "type": "Feature",
      "properties": {
        "id": 107,
        "name": "Clover Toys",
        "type": "Kids Activities",
        "show_label": "",
        "icon": "",
        "show_icon": "",
        "rotate": "",
        "left_panel": "",
        "description": "",
        "details": ""
      },
      "geometry": {
        "type": "Point",
        "coordinates": [
          -122.3845748361699,
          47.66953837178727
        ]
      }
    },
    {
      "type": "Feature",
      "properties": {
        "id": 108,
        "name": "Kid's Deck Main Stage/Tent",
        "type": "Kids Activities",
        "show_label": "",
        "icon": "",
        "show_icon": "",
        "rotate": "",
        "left_panel": "",
        "description": "",
        "details": ""
      },
      "geometry": {
        "type": "Point",
        "coordinates": [
          -122.38464428189522,
          47.66954900022792
        ]
      }
    },
    {
      "type": "Feature",
      "properties": {
        "id": 110,
        "name": "Illumination Learning Studio",
        "type": "Kids Activities",
        "show_label": "",
        "icon": "",
        "show_icon": "",
        "rotate": "",
        "left_panel": "",
        "description": "",
        "details": ""
      },
      "geometry": {
        "type": "Point",
        "coordinates": [
          -122.38468704737551,
          47.669694255366565
        ]
      }
    },
    {
      "type": "Feature",
      "properties": {
        "id": 111,
        "name": "Kym's Corner",
        "type": "Kids Activities",
        "show_label": "",
        "icon": "",
        "show_icon": "",
        "rotate": "",
        "left_panel": "",
        "description": "",
        "details": ""
      },
      "geometry": {
        "type": "Point",
        "coordinates": [
          -122.38468704737551,
          47.66972543202655
        ]
      }
    },
    {
      "type": "Feature",
      "properties": {
        "id": 112,
        "name": "Seattle ReCreative",
        "type": "Kids Activities",
        "show_label": "",
        "icon": "",
        "show_icon": "",
        "rotate": "",
        "left_panel": "",
        "description": "",
        "details": ""
      },
      "geometry": {
        "type": "Point",
        "coordinates": [
          -122.38468704737551,
          47.66977857401769
        ]
      }
    },
    {
      "type": "Feature",
      "properties": {
        "id": 113,
        "name": "Seattle ReCreative",
        "type": "Kids Activities",
        "show_label": "",
        "icon": "",
        "show_icon": "",
        "rotate": "",
        "left_panel": "",
        "description": "",
        "details": ""
      },
      "geometry": {
        "type": "Point",
        "coordinates": [
          -122.38468704737551,
          47.6698090420682
        ]
      }
    },
    {
      "type": "Feature",
      "properties": {
        "id": 114,
        "name": "SGB / Page Ahead",
        "type": "Kids Activities",
        "show_label": "",
        "icon": "",
        "show_icon": "",
        "rotate": "",
        "left_panel": "",
        "description": "",
        "details": ""
      },
      "geometry": {
        "type": "Point",
        "coordinates": [
          -122.38468704737551,
          47.669867852441
        ]
      }
    },
    {
      "type": "Feature",
      "properties": {
        "id": 115,
        "name": "Urban Artworks",
        "type": "Kids Activities",
        "show_label": "",
        "icon": "",
        "show_icon": "",
        "rotate": "",
        "left_panel": "",
        "description": "",
        "details": ""
      },
      "geometry": {
        "type": "Point",
        "coordinates": [
          -122.38462113332012,
          47.669867852441
        ]
      }
    },
    {
      "type": "Feature",
      "properties": {
        "id": 116,
        "name": "Illumination Learning Studio - Jellyfish Shakers",
        "type": "Kids Activities",
        "show_label": "",
        "icon": "",
        "show_icon": "",
        "rotate": "",
        "left_panel": "",
        "description": "",
        "details": ""
      },
      "geometry": {
        "type": "Point",
        "coordinates": [
          -122.38462113332012,
          47.6698090420682
        ]
      }
    },
    {
      "type": "Feature",
      "properties": {
        "id": 117,
        "name": "Mox Boarding House",
        "type": "Kids Activities",
        "show_label": "",
        "icon": "",
        "show_icon": "",
        "rotate": "",
        "left_panel": "",
        "description": "",
        "details": ""
      },
      "geometry": {
        "type": "Point",
        "coordinates": [
          -122.38462113332012,
          47.66977857401769
        ]
      }
    },
    {
      "type": "Feature",
      "properties": {
        "id": 118,
        "name": "Mox Boarding House",
        "type": "Kids Activities",
        "show_label": "",
        "icon": "",
        "show_icon": "",
        "rotate": "",
        "left_panel": "",
        "description": "",
        "details": ""
      },
      "geometry": {
        "type": "Point",
        "coordinates": [
          -122.38462113332012,
          47.66972543202655
        ]
      }
    },
    {
      "type": "Feature",
      "properties": {
        "id": 119,
        "name": "Illumination Learning Studio",
        "type": "Kids Activities",
        "show_label": "",
        "icon": "",
        "show_icon": "",
        "rotate": "",
        "left_panel": "",
        "description": "",
        "details": ""
      },
      "geometry": {
        "type": "Point",
        "coordinates": [
          -122.38462113332012,
          47.669694255366565
        ]
      }
    },
    {
      "type": "Feature",
      "properties": {
        "id": 120,
        "name": "Restrooms",
        "type": "Restroom",
        "show_label": null,
        "icon": "svg_WB",
        "show_icon": "true",
        "rotate": null,
        "left_panel": "",
        "description": null,
        "details": null
      },
      "geometry": {
        "type": "Point",
        "coordinates": [
          -122.38542843845586,
          47.6678909595721
        ]
      }
    },
    {
      "type": "Feature",
      "properties": {
        "id": 121,
        "name": "Restrooms",
        "type": "Restroom",
        "show_label": "",
        "icon": "svg_WB",
        "show_icon": "true",
        "rotate": null,
        "left_panel": "",
        "description": null,
        "details": null
      },
      "geometry": {
        "type": "Point",
        "coordinates": [
          -122.3834965561078,
          47.66856577975249
        ]
      }
    },
    {
      "type": "Feature",
      "properties": {
        "id": 122,
        "name": "Beer + Cocktail Garden Token Sales",
        "type": "Sponsor",
        "show_label": null,
        "icon": "svg_tickets",
        "show_icon": "true",
        "rotate": null,
        "left_panel": null,
        "description": null,
        "details": null
      },
      "geometry": {
        "type": "Point",
        "coordinates": [
          -122.38606303124693,
          47.668561866602836
        ]
      }
    },
    {
      "type": "Feature",
      "properties": {
        "id": 123,
        "name": "Beer + Cocktail Garden Token Sales",
        "type": "Sponsor",
        "show_label": null,
        "icon": "svg_tickets",
        "show_icon": "true",
        "rotate": null,
        "left_panel": null,
        "description": null,
        "details": null
      },
      "geometry": {
        "type": "Point",
        "coordinates": [
          -122.38559379636708,
          47.66803144988907
        ]
      }
    },
    {
      "type": "Feature",
      "properties": {
        "id": 9993,
        "left_panel": "true",
        "name": "Salmon BBQ",
        "rotate": "90",
        "show_icon": "false",
        "show_label": "true",
        "type": "Food Vendor"
      },
      "geometry": {
        "type": "Polygon",
        "coordinates": [
          [
            [
              -122.38468713647,
              47.66881593925
            ],
            [
              -122.38479009181,
              47.66881490465
            ],
            [
              -122.38478924876,
              47.66937505244
            ],
            [
              -122.38468565658,
              47.66937556471
            ],
            [
              -122.38468713647,
              47.66881593925
            ]
          ]
        ]
      }
    },
    {
      "type": "Feature",
      "properties": {
        "id": 9999,
        "left_panel": "true",
        "name": "Beer + Cocktail Garden",
        "rotate": "45",
        "show_icon": null,
        "show_label": "true",
        "type": "Amusement"
      },
      "geometry": {
        "type": "Polygon",
        "coordinates": [
          [
            [
              -122.38603913653,
              47.66861707142
            ],
            [
              -122.38604057739,
              47.66850912185
            ],
            [
              -122.38489601306,
              47.66774875086
            ],
            [
              -122.38497393872,
              47.66769411737
            ],
            [
              -122.38616098094,
              47.66848927306
            ],
            [
              -122.38616102625,
              47.66861868874
            ],
            [
              -122.38603913653,
              47.66861707142
            ]
          ]
        ]
      }
    },
    {
      "type": "Feature",
      "properties": {
        "id": 197,
        "left_panel": "true",
        "name": "Giant European Slide",
        "rotate": null,
        "show_icon": null,
        "show_label": "true",
        "type": "Kids Activities"
      },
      "geometry": {
        "type": "Polygon",
        "coordinates": [
          [
            [
              -122.38477951421,
              47.66985933
            ],
            [
              -122.3847229864,
              47.66985972026
            ],
            [
              -122.38472297991,
              47.66963152006
            ],
            [
              -122.38477950771,
              47.6696311298
            ],
            [
              -122.38477951421,
              47.66985933
            ]
          ]
        ]
      }
    },
    {
      "type": "Feature",
      "properties": {
        "id": 9997,
        "left_panel": "true",
        "name": "Main Stage",
        "rotate": null,
        "show_icon": null,
        "show_label": null,
        "type": "Amusement"
      },
      "geometry": {
        "type": "Polygon",
        "coordinates": [
          [
            [
              -122.38471098099,
              47.66757477168
            ],
            [
              -122.38467051153,
              47.66754160129
            ],
            [
              -122.38475523157,
              47.66749472538
            ],
            [
              -122.38479570103,
              47.6675278958
            ],
            [
              -122.38471098099,
              47.66757477168
            ]
          ]
        ]
      }
    }
  ]
}